amdahl/__init__.py
amdahl/__main__.py
amdahl/amdahl.py
amdahl-0.3.1.dist-info/LICENSE
amdahl-0.3.1.dist-info/METADATA
amdahl-0.3.1.dist-info/WHEEL
amdahl-0.3.1.dist-info/entry_points.txt
amdahl-0.3.1.dist-info/top_level.txt
amdahl-0.3.1.dist-info/RECORD
