Metadata-Version: 2.1
Name: amdahl
Version: 0.3.1
Summary: A pseudo-application that can be used as a black box to reproduce Amdahl's Law
Home-page: https://github.com/ocaisa/amdahl
Author: Alan O'Cais
Author-email: alan.ocais@cecam.org
Requires-Python: >=3
License-File: LICENSE
Requires-Dist: mpi4py
